<?xml version="1.0" encoding="UTF-8"?>
<export version="E">
  <design>
    <source>/__w/test_KDT_Hierarchical_KiBot/test_KDT_Hierarchical_KiBot/KDT_Hierarchical_KiBot.kicad_sch</source>
    <date>2025-12-10T16:40:16+0000</date>
    <tool>Eeschema 9.0.6+1</tool>
    <textvar name="ASSEMBLY_NOTES">ASSEMBLY NOTES (UNLESS OTHERWISE SPECIFIED)

1)	DO NOT POPULATE PARTS ARE MARKED WITH A RED CROSS.

2)	DO NOT POPULATE PARTS ARE NOT PRESENT IN THE BOM.

3)	IF CONFLICTING INFORMATION IS FOUND BETWEEN THE ASSEMBLY
	FILE AND BOM, BOM SHOULD BE USED AS THE MAIN SOURCE.

4)	CONFORMAL COATING IS NOT REQUIRED.

5)	DOT IDENTIFIES PIN #1 LOCATION AND DEVICE ORIENTATION
	WHEN VIEWED FROM THE TOP.</textvar>
    <textvar name="BOARD_NAME">0</textvar>
    <textvar name="COMPANY">INTI</textvar>
    <textvar name="DESIGNER">SET</textvar>
    <textvar name="FABRICATION_NOTES">FABRICATION NOTES (UNLESS OTHERWISE SPECIFIED)

1)	FABRICATE PER IPC-6012A CLASS 2.

2)	OUTLINE DEFINED IN SEPARATE GERBER FILE WITH
	"Edge_Cuts.GBR" SUFFIX.

	DIMENSIONS OF CIRCUMSIZED RECTANGLE SHOWN ON THIS
	DRAWING FOR REFERENCE ONLY.

3)	SEE SEPARATE DRILL FILES WITH ".DRL" SUFFIX 
	FOR HOLE LOCATIONS.

	SELECTED HOLE LOCATIONS SHOWN ON THIS DRAWING 
	FOR REFERENCE ONLY.

4)	SURFACE FINISH: IMMERSION GOLD

5)	SOLDERMASK ON BOTH SIDES OF THE BOARD SHALL 
	BE LPI, COLOR BLACK.

6)	SILK SCREEN LEGEND TO BE APPLIED PER LAYER 
	STACKUP USING YELLOW NON-CONDUCTIVE EPOXY INK.

7)	ALL VIAS ARE TENTED ON BOTH SIDES UNLESS 
	SOLDERMASK OPENED IN GERBER.

8)	VENDOR SHOULD FOLLOW ROHS COMPLIANT PROCESS 
	AND Pb FREE FOR MANUFACTURING

9)	PCB MATERIAL REQUIREMENTS:

	A.	FLAMMABILITY RATING MUST MEET OR EXCEED 
		UL94V-0 REQUIREMENTS.
	B.	Tg 170 C OR EQUIVALENT.
	C.	EQUIVALENT MATERIAL SHALL BE RoHS COMPLIANT, 
		HALOGEN FREE AND APPROVED BY INTI.

10)	DESIGN GEOMETRY MINIMUM FEATURE SIZES:

	BOARD SIZE				63.200 × 35.760 mm
	BOARD THICKNESS		1.660 mm
	TRACE WIDTH			0.381 mm
	TRACE TO TRACE		0.200 mm
	MIN. HOLE (PTH)			0.400 mm
	MIN. HOLE (NPTH)		1.500 mm
	ANNULAR RING			0.200 mm
	COPPER TO HOLE		0.254 mm
	COPPER TO EDGE		0.250 mm
	HOLE TO HOLE			0.254 mm

11)	REFER TO IMPEDANCE TABLE FOR IMPEDANCE CONTROL REQUIREMENTS.

12)	CONFIRM SPACE WIDTHS AND SPACINGS.</textvar>
    <textvar name="GIT_HASH_PCB">d5db5df</textvar>
    <textvar name="GIT_HASH_SCH">c440c30</textvar>
    <textvar name="GIT_URL">https://github.com/set-soft/test_KDT_Hierarchical_KiBot</textvar>
    <textvar name="PROJECT_NAME">Test KDT</textvar>
    <textvar name="RELEASE_BODY_1.0.0"/>
    <textvar name="RELEASE_BODY_1.0.1"/>
    <textvar name="RELEASE_BODY_1.0.2"/>
    <textvar name="RELEASE_BODY_1.1.0"/>
    <textvar name="RELEASE_BODY_UNRELEASED">Version Unreleased not found.</textvar>
    <textvar name="RELEASE_DATE">10-Dec-2025</textvar>
    <textvar name="RELEASE_DATE_NUM">2025-12-10</textvar>
    <textvar name="RELEASE_TITLE_1.0.0"/>
    <textvar name="RELEASE_TITLE_1.0.1"/>
    <textvar name="RELEASE_TITLE_1.0.2"/>
    <textvar name="RELEASE_TITLE_1.1.0"/>
    <textvar name="RELEASE_TITLE_UNRELEASED">Version Unreleased not found.</textvar>
    <textvar name="REVISION">+ (Unreleased)</textvar>
    <textvar name="SHEET_NAME_1">Cover Page</textvar>
    <textvar name="SHEET_NAME_10">......................................</textvar>
    <textvar name="SHEET_NAME_11">......................................</textvar>
    <textvar name="SHEET_NAME_12">......................................</textvar>
    <textvar name="SHEET_NAME_13">......................................</textvar>
    <textvar name="SHEET_NAME_14">......................................</textvar>
    <textvar name="SHEET_NAME_15">......................................</textvar>
    <textvar name="SHEET_NAME_16">......................................</textvar>
    <textvar name="SHEET_NAME_17">......................................</textvar>
    <textvar name="SHEET_NAME_18">......................................</textvar>
    <textvar name="SHEET_NAME_19">......................................</textvar>
    <textvar name="SHEET_NAME_2">Block Diagram</textvar>
    <textvar name="SHEET_NAME_20">......................................</textvar>
    <textvar name="SHEET_NAME_21">......................................</textvar>
    <textvar name="SHEET_NAME_22">......................................</textvar>
    <textvar name="SHEET_NAME_23">......................................</textvar>
    <textvar name="SHEET_NAME_24">......................................</textvar>
    <textvar name="SHEET_NAME_25">......................................</textvar>
    <textvar name="SHEET_NAME_26">......................................</textvar>
    <textvar name="SHEET_NAME_27">......................................</textvar>
    <textvar name="SHEET_NAME_28">......................................</textvar>
    <textvar name="SHEET_NAME_29">......................................</textvar>
    <textvar name="SHEET_NAME_3">Project Architecture</textvar>
    <textvar name="SHEET_NAME_30">......................................</textvar>
    <textvar name="SHEET_NAME_31">......................................</textvar>
    <textvar name="SHEET_NAME_32">......................................</textvar>
    <textvar name="SHEET_NAME_33">......................................</textvar>
    <textvar name="SHEET_NAME_34">......................................</textvar>
    <textvar name="SHEET_NAME_35">......................................</textvar>
    <textvar name="SHEET_NAME_36">......................................</textvar>
    <textvar name="SHEET_NAME_37">......................................</textvar>
    <textvar name="SHEET_NAME_38">......................................</textvar>
    <textvar name="SHEET_NAME_39">......................................</textvar>
    <textvar name="SHEET_NAME_4">Section A - Title A</textvar>
    <textvar name="SHEET_NAME_40">......................................</textvar>
    <textvar name="SHEET_NAME_5">Section B - Title B</textvar>
    <textvar name="SHEET_NAME_6">Power - Sequencing</textvar>
    <textvar name="SHEET_NAME_7">Revision History</textvar>
    <textvar name="SHEET_NAME_8">......................................</textvar>
    <textvar name="SHEET_NAME_9">......................................</textvar>
    <textvar name="VARIANT">PRELIMINARY</textvar>
    <sheet number="1" name="/" tstamps="/">
      <title_block>
        <title/>
        <company>INTI</company>
        <rev>+ (Unreleased)</rev>
        <date>2025-01-12</date>
        <source>KDT_Hierarchical_KiBot.kicad_sch</source>
        <comment number="1" value=""/>
        <comment number="2" value=""/>
        <comment number="3" value=""/>
        <comment number="4" value=""/>
        <comment number="5" value=""/>
        <comment number="6" value=""/>
        <comment number="7" value=""/>
        <comment number="8" value=""/>
        <comment number="9" value=""/>
      </title_block>
    </sheet>
    <sheet number="2" name="/Block Diagram/" tstamps="/82da9dbf-ba38-4d08-ba35-a220fa2963b1/">
      <title_block>
        <title>Block Diagram</title>
        <company>INTI</company>
        <rev>+ (Unreleased)</rev>
        <date>2025-01-12</date>
        <source>Block Diagram.kicad_sch</source>
        <comment number="1" value=""/>
        <comment number="2" value=""/>
        <comment number="3" value=""/>
        <comment number="4" value=""/>
        <comment number="5" value=""/>
        <comment number="6" value=""/>
        <comment number="7" value=""/>
        <comment number="8" value=""/>
        <comment number="9" value=""/>
      </title_block>
    </sheet>
    <sheet number="3" name="/Project Architecture/" tstamps="/c5103ceb-5325-4a84-a025-9638a412984e/">
      <title_block>
        <title>Project Architecture</title>
        <company>INTI</company>
        <rev>+ (Unreleased)</rev>
        <date>2025-01-12</date>
        <source>Project Architecture.kicad_sch</source>
        <comment number="1" value=""/>
        <comment number="2" value=""/>
        <comment number="3" value=""/>
        <comment number="4" value=""/>
        <comment number="5" value=""/>
        <comment number="6" value=""/>
        <comment number="7" value=""/>
        <comment number="8" value=""/>
        <comment number="9" value=""/>
      </title_block>
    </sheet>
    <sheet number="4" name="/Project Architecture/Section A - Title A/" tstamps="/c5103ceb-5325-4a84-a025-9638a412984e/f06537ee-772d-44d3-8c50-e0ba41038c9c/">
      <title_block>
        <title>Sheet Title A</title>
        <company>INTI</company>
        <rev>+ (Unreleased)</rev>
        <date>2025-01-12</date>
        <source>Section A - Title A.kicad_sch</source>
        <comment number="1" value=""/>
        <comment number="2" value=""/>
        <comment number="3" value=""/>
        <comment number="4" value=""/>
        <comment number="5" value=""/>
        <comment number="6" value=""/>
        <comment number="7" value=""/>
        <comment number="8" value=""/>
        <comment number="9" value=""/>
      </title_block>
    </sheet>
    <sheet number="5" name="/Project Architecture/Section B - Title B/" tstamps="/c5103ceb-5325-4a84-a025-9638a412984e/e744f3ce-03a6-44a6-8792-1447ef232b9a/">
      <title_block>
        <title>Sheet Title B</title>
        <company>INTI</company>
        <rev>+ (Unreleased)</rev>
        <date>2025-01-12</date>
        <source>Section B - TItle B.kicad_sch</source>
        <comment number="1" value=""/>
        <comment number="2" value=""/>
        <comment number="3" value=""/>
        <comment number="4" value=""/>
        <comment number="5" value=""/>
        <comment number="6" value=""/>
        <comment number="7" value=""/>
        <comment number="8" value=""/>
        <comment number="9" value=""/>
      </title_block>
    </sheet>
    <sheet number="6" name="/Power - Sequencing/" tstamps="/5fb05893-0da3-4f58-a52b-cb6d6f4cb80b/">
      <title_block>
        <title>Power - Sequencing</title>
        <company>INTI</company>
        <rev>+ (Unreleased)</rev>
        <date>2025-01-12</date>
        <source>Power - Sequencing.kicad_sch</source>
        <comment number="1" value=""/>
        <comment number="2" value=""/>
        <comment number="3" value=""/>
        <comment number="4" value=""/>
        <comment number="5" value=""/>
        <comment number="6" value=""/>
        <comment number="7" value=""/>
        <comment number="8" value=""/>
        <comment number="9" value=""/>
      </title_block>
    </sheet>
    <sheet number="7" name="/Revision History/" tstamps="/6e125bd6-2f99-4e5d-b3ea-4899f4540739/">
      <title_block>
        <title>Revision History</title>
        <company>INTI</company>
        <rev>+ (Unreleased)</rev>
        <date>2025-01-12</date>
        <source>Revision History.kicad_sch</source>
        <comment number="1" value=""/>
        <comment number="2" value=""/>
        <comment number="3" value=""/>
        <comment number="4" value=""/>
        <comment number="5" value=""/>
        <comment number="6" value=""/>
        <comment number="7" value=""/>
        <comment number="8" value=""/>
        <comment number="9" value=""/>
      </title_block>
    </sheet>
  </design>
  <components>
    <comp ref="C1">
      <value>47uF</value>
      <footprint>Capacitor_SMD:CP_Elec_8x10</footprint>
      <datasheet>~</datasheet>
      <description>Polarized capacitor</description>
      <fields>
        <field name="MFN">Vishay Beyschlag/Draloric/BC Components</field>
        <field name="MFP">MAL215371479E3</field>
        <field name="Footprint">Capacitor_SMD:CP_Elec_8x10</field>
        <field name="Datasheet">~</field>
        <field name="Description">Polarized capacitor</field>
      </fields>
      <libsource lib="Device" part="C_Polarized" description="Polarized capacitor"/>
      <property name="MFN" value="Vishay Beyschlag/Draloric/BC Components"/>
      <property name="MFP" value="MAL215371479E3"/>
      <property name="Sheetname" value="Section A - Title A"/>
      <property name="Sheetfile" value="Section A - Title A.kicad_sch"/>
      <property name="ki_keywords" value="cap capacitor"/>
      <property name="ki_fp_filters" value="CP_*"/>
      <sheetpath names="/Project Architecture/Section A - Title A/" tstamps="/c5103ceb-5325-4a84-a025-9638a412984e/f06537ee-772d-44d3-8c50-e0ba41038c9c/"/>
      <tstamps>00000000-0000-0000-0000-00005f77f6ad</tstamps>
    </comp>
    <comp ref="C2">
      <value>100nF</value>
      <footprint>Capacitor_SMD:C_0805_2012Metric</footprint>
      <datasheet>~</datasheet>
      <description>Unpolarized capacitor</description>
      <fields>
        <field name="Footprint">Capacitor_SMD:C_0805_2012Metric</field>
        <field name="Datasheet">~</field>
        <field name="Description">Unpolarized capacitor</field>
      </fields>
      <libsource lib="Device" part="C" description="Unpolarized capacitor"/>
      <property name="Sheetname" value="Section A - Title A"/>
      <property name="Sheetfile" value="Section A - Title A.kicad_sch"/>
      <property name="ki_keywords" value="cap capacitor"/>
      <property name="ki_fp_filters" value="C_*"/>
      <sheetpath names="/Project Architecture/Section A - Title A/" tstamps="/c5103ceb-5325-4a84-a025-9638a412984e/f06537ee-772d-44d3-8c50-e0ba41038c9c/"/>
      <tstamps>00000000-0000-0000-0000-00005f795151</tstamps>
    </comp>
    <comp ref="C3">
      <value>22pF</value>
      <footprint>Capacitor_SMD:C_0805_2012Metric</footprint>
      <datasheet>~</datasheet>
      <description>Unpolarized capacitor</description>
      <fields>
        <field name="Config">+USB,+XTAL</field>
        <field name="Footprint">Capacitor_SMD:C_0805_2012Metric</field>
        <field name="Datasheet">~</field>
        <field name="Description">Unpolarized capacitor</field>
      </fields>
      <libsource lib="Device" part="C" description="Unpolarized capacitor"/>
      <property name="Config" value="+USB,+XTAL"/>
      <property name="Sheetname" value="Section A - Title A"/>
      <property name="Sheetfile" value="Section A - Title A.kicad_sch"/>
      <property name="ki_keywords" value="cap capacitor"/>
      <property name="ki_fp_filters" value="C_*"/>
      <sheetpath names="/Project Architecture/Section A - Title A/" tstamps="/c5103ceb-5325-4a84-a025-9638a412984e/f06537ee-772d-44d3-8c50-e0ba41038c9c/"/>
      <tstamps>00000000-0000-0000-0000-00005f592c96</tstamps>
    </comp>
    <comp ref="C4">
      <value>22pF</value>
      <footprint>Capacitor_SMD:C_0805_2012Metric</footprint>
      <datasheet>~</datasheet>
      <description>Unpolarized capacitor</description>
      <fields>
        <field name="Config">+USB,+XTAL</field>
        <field name="Footprint">Capacitor_SMD:C_0805_2012Metric</field>
        <field name="Datasheet">~</field>
        <field name="Description">Unpolarized capacitor</field>
      </fields>
      <libsource lib="Device" part="C" description="Unpolarized capacitor"/>
      <property name="Config" value="+USB,+XTAL"/>
      <property name="Sheetname" value="Section A - Title A"/>
      <property name="Sheetfile" value="Section A - Title A.kicad_sch"/>
      <property name="ki_keywords" value="cap capacitor"/>
      <property name="ki_fp_filters" value="C_*"/>
      <sheetpath names="/Project Architecture/Section A - Title A/" tstamps="/c5103ceb-5325-4a84-a025-9638a412984e/f06537ee-772d-44d3-8c50-e0ba41038c9c/"/>
      <tstamps>00000000-0000-0000-0000-00005f59130a</tstamps>
    </comp>
    <comp ref="C5">
      <value>1uF</value>
      <footprint>Capacitor_SMD:C_0805_2012Metric</footprint>
      <datasheet>~</datasheet>
      <description>Unpolarized capacitor</description>
      <fields>
        <field name="Footprint">Capacitor_SMD:C_0805_2012Metric</field>
        <field name="Datasheet">~</field>
        <field name="Description">Unpolarized capacitor</field>
      </fields>
      <libsource lib="Device" part="C" description="Unpolarized capacitor"/>
      <property name="Sheetname" value="Section A - Title A"/>
      <property name="Sheetfile" value="Section A - Title A.kicad_sch"/>
      <property name="ki_keywords" value="cap capacitor"/>
      <property name="ki_fp_filters" value="C_*"/>
      <sheetpath names="/Project Architecture/Section A - Title A/" tstamps="/c5103ceb-5325-4a84-a025-9638a412984e/f06537ee-772d-44d3-8c50-e0ba41038c9c/"/>
      <tstamps>00000000-0000-0000-0000-00005f5bb617</tstamps>
    </comp>
    <comp ref="C6">
      <value>100nF</value>
      <footprint>Capacitor_SMD:C_0805_2012Metric</footprint>
      <datasheet>~</datasheet>
      <description>Unpolarized capacitor</description>
      <fields>
        <field name="Footprint">Capacitor_SMD:C_0805_2012Metric</field>
        <field name="Datasheet">~</field>
        <field name="Description">Unpolarized capacitor</field>
      </fields>
      <libsource lib="Device" part="C" description="Unpolarized capacitor"/>
      <property name="Sheetname" value="Section A - Title A"/>
      <property name="Sheetfile" value="Section A - Title A.kicad_sch"/>
      <property name="ki_keywords" value="cap capacitor"/>
      <property name="ki_fp_filters" value="C_*"/>
      <sheetpath names="/Project Architecture/Section A - Title A/" tstamps="/c5103ceb-5325-4a84-a025-9638a412984e/f06537ee-772d-44d3-8c50-e0ba41038c9c/"/>
      <tstamps>00000000-0000-0000-0000-00005f5c6e57</tstamps>
    </comp>
    <comp ref="C7">
      <value>100nF</value>
      <footprint>Capacitor_SMD:C_0805_2012Metric</footprint>
      <datasheet>~</datasheet>
      <description>Unpolarized capacitor</description>
      <fields>
        <field name="Footprint">Capacitor_SMD:C_0805_2012Metric</field>
        <field name="Datasheet">~</field>
        <field name="Description">Unpolarized capacitor</field>
      </fields>
      <libsource lib="Device" part="C" description="Unpolarized capacitor"/>
      <property name="Sheetname" value="Section A - Title A"/>
      <property name="Sheetfile" value="Section A - Title A.kicad_sch"/>
      <property name="ki_keywords" value="cap capacitor"/>
      <property name="ki_fp_filters" value="C_*"/>
      <sheetpath names="/Project Architecture/Section A - Title A/" tstamps="/c5103ceb-5325-4a84-a025-9638a412984e/f06537ee-772d-44d3-8c50-e0ba41038c9c/"/>
      <tstamps>00000000-0000-0000-0000-00005f74311f</tstamps>
    </comp>
    <comp ref="C8">
      <value>100nF</value>
      <footprint>Capacitor_SMD:C_0805_2012Metric</footprint>
      <datasheet>~</datasheet>
      <description>Unpolarized capacitor</description>
      <fields>
        <field name="Footprint">Capacitor_SMD:C_0805_2012Metric</field>
        <field name="Datasheet">~</field>
        <field name="Description">Unpolarized capacitor</field>
      </fields>
      <libsource lib="Device" part="C" description="Unpolarized capacitor"/>
      <property name="Sheetname" value="Section A - Title A"/>
      <property name="Sheetfile" value="Section A - Title A.kicad_sch"/>
      <property name="ki_keywords" value="cap capacitor"/>
      <property name="ki_fp_filters" value="C_*"/>
      <sheetpath names="/Project Architecture/Section A - Title A/" tstamps="/c5103ceb-5325-4a84-a025-9638a412984e/f06537ee-772d-44d3-8c50-e0ba41038c9c/"/>
      <tstamps>00000000-0000-0000-0000-00005f6f7fd9</tstamps>
    </comp>
    <comp ref="D1">
      <value>CD1206-S01575</value>
      <footprint>Diode_SMD:D_1206_3216Metric</footprint>
      <datasheet>~</datasheet>
      <description>Diode</description>
      <fields>
        <field name="Sim.Device">D</field>
        <field name="Sim.Pins">1=K 2=A</field>
        <field name="Footprint">Diode_SMD:D_1206_3216Metric</field>
        <field name="Datasheet">~</field>
        <field name="Description">Diode</field>
      </fields>
      <libsource lib="Device" part="D" description="Diode"/>
      <property name="Sim.Device" value="D"/>
      <property name="Sim.Pins" value="1=K 2=A"/>
      <property name="Sheetname" value="Section A - Title A"/>
      <property name="Sheetfile" value="Section A - Title A.kicad_sch"/>
      <property name="ki_keywords" value="diode"/>
      <property name="ki_fp_filters" value="TO-???* *_Diode_* *SingleDiode* D_*"/>
      <sheetpath names="/Project Architecture/Section A - Title A/" tstamps="/c5103ceb-5325-4a84-a025-9638a412984e/f06537ee-772d-44d3-8c50-e0ba41038c9c/"/>
      <tstamps>00000000-0000-0000-0000-00005f5e34dd</tstamps>
    </comp>
    <comp ref="D2">
      <value>LED</value>
      <footprint>LED_SMD:LED_0805_2012Metric</footprint>
      <datasheet>~</datasheet>
      <description>Light emitting diode</description>
      <fields>
        <field name="MFN">OSRAM Opto Semiconductors Inc.</field>
        <field name="MFP">LG R971-KN-1</field>
        <field name="Footprint">LED_SMD:LED_0805_2012Metric</field>
        <field name="Datasheet">~</field>
        <field name="Description">Light emitting diode</field>
      </fields>
      <libsource lib="Device" part="LED" description="Light emitting diode"/>
      <property name="MFN" value="OSRAM Opto Semiconductors Inc."/>
      <property name="MFP" value="LG R971-KN-1"/>
      <property name="Sheetname" value="Section A - Title A"/>
      <property name="Sheetfile" value="Section A - Title A.kicad_sch"/>
      <property name="ki_keywords" value="LED diode"/>
      <property name="ki_fp_filters" value="LED* LED_SMD:* LED_THT:*"/>
      <sheetpath names="/Project Architecture/Section A - Title A/" tstamps="/c5103ceb-5325-4a84-a025-9638a412984e/f06537ee-772d-44d3-8c50-e0ba41038c9c/"/>
      <tstamps>00000000-0000-0000-0000-00005f6c8805</tstamps>
    </comp>
    <comp ref="D3">
      <value>LED</value>
      <footprint>LED_SMD:LED_0805_2012Metric</footprint>
      <datasheet>~</datasheet>
      <description>Light emitting diode</description>
      <fields>
        <field name="MFN">OSRAM Opto Semiconductors Inc.</field>
        <field name="MFP">LG R971-KN-1</field>
        <field name="Footprint">LED_SMD:LED_0805_2012Metric</field>
        <field name="Datasheet">~</field>
        <field name="Description">Light emitting diode</field>
      </fields>
      <libsource lib="Device" part="LED" description="Light emitting diode"/>
      <property name="MFN" value="OSRAM Opto Semiconductors Inc."/>
      <property name="MFP" value="LG R971-KN-1"/>
      <property name="Sheetname" value="Section A - Title A"/>
      <property name="Sheetfile" value="Section A - Title A.kicad_sch"/>
      <property name="ki_keywords" value="LED diode"/>
      <property name="ki_fp_filters" value="LED* LED_SMD:* LED_THT:*"/>
      <sheetpath names="/Project Architecture/Section A - Title A/" tstamps="/c5103ceb-5325-4a84-a025-9638a412984e/f06537ee-772d-44d3-8c50-e0ba41038c9c/"/>
      <tstamps>00000000-0000-0000-0000-00005f5b927e</tstamps>
    </comp>
    <comp ref="F1">
      <value>MF-MSMF050-2</value>
      <footprint>Resistor_SMD:R_1812_4532Metric</footprint>
      <datasheet>~</datasheet>
      <description>Resettable fuse, polymeric positive temperature coefficient</description>
      <fields>
        <field name="Config">+USB</field>
        <field name="Footprint">Resistor_SMD:R_1812_4532Metric</field>
        <field name="Datasheet">~</field>
        <field name="Description">Resettable fuse, polymeric positive temperature coefficient</field>
      </fields>
      <libsource lib="Device" part="Polyfuse" description="Resettable fuse, polymeric positive temperature coefficient"/>
      <property name="Config" value="+USB"/>
      <property name="Sheetname" value="Section A - Title A"/>
      <property name="Sheetfile" value="Section A - Title A.kicad_sch"/>
      <property name="ki_keywords" value="resettable fuse PTC PPTC polyfuse polyswitch"/>
      <property name="ki_fp_filters" value="*polyfuse* *PTC*"/>
      <sheetpath names="/Project Architecture/Section A - Title A/" tstamps="/c5103ceb-5325-4a84-a025-9638a412984e/f06537ee-772d-44d3-8c50-e0ba41038c9c/"/>
      <tstamps>00000000-0000-0000-0000-00005f5a70cb</tstamps>
    </comp>
    <comp ref="FB1">
      <value>BLM21PG221SN1D</value>
      <footprint>Resistor_SMD:R_0805_2012Metric</footprint>
      <datasheet>~</datasheet>
      <description>Ferrite bead</description>
      <fields>
        <field name="MFN">Murata</field>
        <field name="MFP">BLM21PG221SN1D</field>
        <field name="Config">+USB</field>
        <field name="Footprint">Resistor_SMD:R_0805_2012Metric</field>
        <field name="Datasheet">~</field>
        <field name="Description">Ferrite bead</field>
      </fields>
      <libsource lib="Device" part="FerriteBead" description="Ferrite bead"/>
      <property name="MFN" value="Murata"/>
      <property name="MFP" value="BLM21PG221SN1D"/>
      <property name="Config" value="+USB"/>
      <property name="Sheetname" value="Section A - Title A"/>
      <property name="Sheetfile" value="Section A - Title A.kicad_sch"/>
      <property name="ki_keywords" value="L ferrite bead inductor filter"/>
      <property name="ki_fp_filters" value="Inductor_* L_* *Ferrite*"/>
      <sheetpath names="/Project Architecture/Section A - Title A/" tstamps="/c5103ceb-5325-4a84-a025-9638a412984e/f06537ee-772d-44d3-8c50-e0ba41038c9c/"/>
      <tstamps>00000000-0000-0000-0000-00005f5a5e4b</tstamps>
    </comp>
    <comp ref="FID1">
      <value>Fiducial</value>
      <footprint>Fiducial:Fiducial_0.75mm_Mask1.5mm</footprint>
      <datasheet>~</datasheet>
      <description>Fiducial Marker</description>
      <fields>
        <field name="Footprint">Fiducial:Fiducial_0.75mm_Mask1.5mm</field>
        <field name="Datasheet">~</field>
        <field name="Description">Fiducial Marker</field>
      </fields>
      <libsource lib="Mechanical" part="Fiducial" description="Fiducial Marker"/>
      <property name="Sheetname" value="Section A - Title A"/>
      <property name="Sheetfile" value="Section A - Title A.kicad_sch"/>
      <property name="ki_keywords" value="fiducial marker"/>
      <property name="ki_fp_filters" value="Fiducial*"/>
      <sheetpath names="/Project Architecture/Section A - Title A/" tstamps="/c5103ceb-5325-4a84-a025-9638a412984e/f06537ee-772d-44d3-8c50-e0ba41038c9c/"/>
      <tstamps>00000000-0000-0000-0000-00005f82bd5c</tstamps>
    </comp>
    <comp ref="FID2">
      <value>Fiducial</value>
      <footprint>Fiducial:Fiducial_0.75mm_Mask1.5mm</footprint>
      <datasheet>~</datasheet>
      <description>Fiducial Marker</description>
      <fields>
        <field name="Footprint">Fiducial:Fiducial_0.75mm_Mask1.5mm</field>
        <field name="Datasheet">~</field>
        <field name="Description">Fiducial Marker</field>
      </fields>
      <libsource lib="Mechanical" part="Fiducial" description="Fiducial Marker"/>
      <property name="Sheetname" value="Section A - Title A"/>
      <property name="Sheetfile" value="Section A - Title A.kicad_sch"/>
      <property name="ki_keywords" value="fiducial marker"/>
      <property name="ki_fp_filters" value="Fiducial*"/>
      <sheetpath names="/Project Architecture/Section A - Title A/" tstamps="/c5103ceb-5325-4a84-a025-9638a412984e/f06537ee-772d-44d3-8c50-e0ba41038c9c/"/>
      <tstamps>00000000-0000-0000-0000-00005f83c5e8</tstamps>
    </comp>
    <comp ref="FID3">
      <value>Fiducial</value>
      <footprint>Fiducial:Fiducial_0.75mm_Mask1.5mm</footprint>
      <datasheet>~</datasheet>
      <description>Fiducial Marker</description>
      <fields>
        <field name="Footprint">Fiducial:Fiducial_0.75mm_Mask1.5mm</field>
        <field name="Datasheet">~</field>
        <field name="Description">Fiducial Marker</field>
      </fields>
      <libsource lib="Mechanical" part="Fiducial" description="Fiducial Marker"/>
      <property name="Sheetname" value="Section A - Title A"/>
      <property name="Sheetfile" value="Section A - Title A.kicad_sch"/>
      <property name="ki_keywords" value="fiducial marker"/>
      <property name="ki_fp_filters" value="Fiducial*"/>
      <sheetpath names="/Project Architecture/Section A - Title A/" tstamps="/c5103ceb-5325-4a84-a025-9638a412984e/f06537ee-772d-44d3-8c50-e0ba41038c9c/"/>
      <tstamps>00000000-0000-0000-0000-00005f844210</tstamps>
    </comp>
    <comp ref="FID4">
      <value>Fiducial</value>
      <footprint>Fiducial:Fiducial_0.75mm_Mask1.5mm</footprint>
      <datasheet>~</datasheet>
      <description>Fiducial Marker</description>
      <fields>
        <field name="Footprint">Fiducial:Fiducial_0.75mm_Mask1.5mm</field>
        <field name="Datasheet">~</field>
        <field name="Description">Fiducial Marker</field>
      </fields>
      <libsource lib="Mechanical" part="Fiducial" description="Fiducial Marker"/>
      <property name="Sheetname" value="Section A - Title A"/>
      <property name="Sheetfile" value="Section A - Title A.kicad_sch"/>
      <property name="ki_keywords" value="fiducial marker"/>
      <property name="ki_fp_filters" value="Fiducial*"/>
      <sheetpath names="/Project Architecture/Section A - Title A/" tstamps="/c5103ceb-5325-4a84-a025-9638a412984e/f06537ee-772d-44d3-8c50-e0ba41038c9c/"/>
      <tstamps>00000000-0000-0000-0000-00005f84421a</tstamps>
    </comp>
    <comp ref="H1">
      <value>MountingHole</value>
      <footprint>MountingHole:MountingHole_2.7mm_M2.5</footprint>
      <datasheet>~</datasheet>
      <description>Mounting Hole without connection</description>
      <fields>
        <field name="Footprint">MountingHole:MountingHole_2.7mm_M2.5</field>
        <field name="Datasheet">~</field>
        <field name="Description">Mounting Hole without connection</field>
      </fields>
      <libsource lib="Mechanical" part="MountingHole" description="Mounting Hole without connection"/>
      <property name="Sheetname" value="Section A - Title A"/>
      <property name="Sheetfile" value="Section A - Title A.kicad_sch"/>
      <property name="ki_keywords" value="mounting hole"/>
      <property name="ki_fp_filters" value="MountingHole*"/>
      <sheetpath names="/Project Architecture/Section A - Title A/" tstamps="/c5103ceb-5325-4a84-a025-9638a412984e/f06537ee-772d-44d3-8c50-e0ba41038c9c/"/>
      <tstamps>00000000-0000-0000-0000-00005f854948</tstamps>
    </comp>
    <comp ref="H2">
      <value>MountingHole</value>
      <footprint>MountingHole:MountingHole_2.7mm_M2.5</footprint>
      <datasheet>~</datasheet>
      <description>Mounting Hole without connection</description>
      <fields>
        <field name="Footprint">MountingHole:MountingHole_2.7mm_M2.5</field>
        <field name="Datasheet">~</field>
        <field name="Description">Mounting Hole without connection</field>
      </fields>
      <libsource lib="Mechanical" part="MountingHole" description="Mounting Hole without connection"/>
      <property name="Sheetname" value="Section A - Title A"/>
      <property name="Sheetfile" value="Section A - Title A.kicad_sch"/>
      <property name="ki_keywords" value="mounting hole"/>
      <property name="ki_fp_filters" value="MountingHole*"/>
      <sheetpath names="/Project Architecture/Section A - Title A/" tstamps="/c5103ceb-5325-4a84-a025-9638a412984e/f06537ee-772d-44d3-8c50-e0ba41038c9c/"/>
      <tstamps>00000000-0000-0000-0000-00005f84c851</tstamps>
    </comp>
    <comp ref="H3">
      <value>MountingHole</value>
      <footprint>MountingHole:MountingHole_2.7mm_M2.5</footprint>
      <datasheet>~</datasheet>
      <description>Mounting Hole without connection</description>
      <fields>
        <field name="Footprint">MountingHole:MountingHole_2.7mm_M2.5</field>
        <field name="Datasheet">~</field>
        <field name="Description">Mounting Hole without connection</field>
      </fields>
      <libsource lib="Mechanical" part="MountingHole" description="Mounting Hole without connection"/>
      <property name="Sheetname" value="Section A - Title A"/>
      <property name="Sheetfile" value="Section A - Title A.kicad_sch"/>
      <property name="ki_keywords" value="mounting hole"/>
      <property name="ki_fp_filters" value="MountingHole*"/>
      <sheetpath names="/Project Architecture/Section A - Title A/" tstamps="/c5103ceb-5325-4a84-a025-9638a412984e/f06537ee-772d-44d3-8c50-e0ba41038c9c/"/>
      <tstamps>00000000-0000-0000-0000-00005f854952</tstamps>
    </comp>
    <comp ref="H4">
      <value>MountingHole</value>
      <footprint>MountingHole:MountingHole_2.7mm_M2.5</footprint>
      <datasheet>~</datasheet>
      <description>Mounting Hole without connection</description>
      <fields>
        <field name="Footprint">MountingHole:MountingHole_2.7mm_M2.5</field>
        <field name="Datasheet">~</field>
        <field name="Description">Mounting Hole without connection</field>
      </fields>
      <libsource lib="Mechanical" part="MountingHole" description="Mounting Hole without connection"/>
      <property name="Sheetname" value="Section A - Title A"/>
      <property name="Sheetfile" value="Section A - Title A.kicad_sch"/>
      <property name="ki_keywords" value="mounting hole"/>
      <property name="ki_fp_filters" value="MountingHole*"/>
      <sheetpath names="/Project Architecture/Section A - Title A/" tstamps="/c5103ceb-5325-4a84-a025-9638a412984e/f06537ee-772d-44d3-8c50-e0ba41038c9c/"/>
      <tstamps>00000000-0000-0000-0000-00005f84cd24</tstamps>
    </comp>
    <comp ref="J1">
      <value>Barrel_Jack_Switch</value>
      <footprint>Connector_BarrelJack:BarrelJack_CLIFF_FC681465S_SMT_Horizontal</footprint>
      <datasheet>~</datasheet>
      <description>DC Barrel Jack with an internal switch</description>
      <fields>
        <field name="MFN">Würth Elektronik</field>
        <field name="MFP">694106106102</field>
        <field name="Footprint">Connector_BarrelJack:BarrelJack_CLIFF_FC681465S_SMT_Horizontal</field>
        <field name="Datasheet">~</field>
        <field name="Description">DC Barrel Jack with an internal switch</field>
      </fields>
      <libsource lib="Connector" part="Barrel_Jack_Switch" description="DC Barrel Jack with an internal switch"/>
      <property name="MFN" value="Würth Elektronik"/>
      <property name="MFP" value="694106106102"/>
      <property name="Sheetname" value="Section A - Title A"/>
      <property name="Sheetfile" value="Section A - Title A.kicad_sch"/>
      <property name="ki_keywords" value="DC power barrel jack connector"/>
      <property name="ki_fp_filters" value="BarrelJack*"/>
      <sheetpath names="/Project Architecture/Section A - Title A/" tstamps="/c5103ceb-5325-4a84-a025-9638a412984e/f06537ee-772d-44d3-8c50-e0ba41038c9c/"/>
      <tstamps>00000000-0000-0000-0000-00005f5c2322</tstamps>
    </comp>
    <comp ref="J2">
      <value>USB_B</value>
      <footprint>Connector_USB:USB_B_Lumberg_2411_02_Horizontal</footprint>
      <datasheet>~</datasheet>
      <description>USB Type B connector</description>
      <fields>
        <field name="MFN">TE Connectivity AMP Connectors</field>
        <field name="MFP">292304-1</field>
        <field name="Config">+USB</field>
        <field name="Footprint">Connector_USB:USB_B_Lumberg_2411_02_Horizontal</field>
        <field name="Datasheet">~</field>
        <field name="Description">USB Type B connector</field>
      </fields>
      <libsource lib="Connector" part="USB_B" description="USB Type B connector"/>
      <property name="MFN" value="TE Connectivity AMP Connectors"/>
      <property name="MFP" value="292304-1"/>
      <property name="Config" value="+USB"/>
      <property name="Sheetname" value="Section A - Title A"/>
      <property name="Sheetfile" value="Section A - Title A.kicad_sch"/>
      <property name="ki_keywords" value="connector USB"/>
      <property name="ki_fp_filters" value="USB*"/>
      <sheetpath names="/Project Architecture/Section A - Title A/" tstamps="/c5103ceb-5325-4a84-a025-9638a412984e/f06537ee-772d-44d3-8c50-e0ba41038c9c/"/>
      <tstamps>00000000-0000-0000-0000-00005f5a1098</tstamps>
    </comp>
    <comp ref="J3">
      <value>P1</value>
      <footprint>Connector_PinHeader_2.54mm:PinHeader_1x05_P2.54mm_Vertical</footprint>
      <datasheet>~</datasheet>
      <description>Generic connector, single row, 01x05, script generated</description>
      <fields>
        <field name="Footprint">Connector_PinHeader_2.54mm:PinHeader_1x05_P2.54mm_Vertical</field>
        <field name="Datasheet">~</field>
        <field name="Description">Generic connector, single row, 01x05, script generated</field>
      </fields>
      <libsource lib="Connector" part="Conn_01x05_Pin" description="Generic connector, single row, 01x05, script generated"/>
      <property name="Sheetname" value="Section A - Title A"/>
      <property name="Sheetfile" value="Section A - Title A.kicad_sch"/>
      <property name="ki_keywords" value="connector"/>
      <property name="ki_fp_filters" value="Connector*:*_1x??_*"/>
      <sheetpath names="/Project Architecture/Section A - Title A/" tstamps="/c5103ceb-5325-4a84-a025-9638a412984e/f06537ee-772d-44d3-8c50-e0ba41038c9c/"/>
      <tstamps>00000000-0000-0000-0000-00005f69bb94</tstamps>
    </comp>
    <comp ref="J4">
      <value>2x2M</value>
      <footprint>Connector_PinHeader_2.54mm:PinHeader_2x02_P2.54mm_Vertical</footprint>
      <datasheet>~</datasheet>
      <description>Generic connector, double row, 02x02, odd/even pin numbering scheme (row 1 odd numbers, row 2 even numbers), script generated (kicad-library-utils/schlib/autogen/connector/)</description>
      <fields>
        <field name="MFN">Harwin Inc.</field>
        <field name="MFP">M20-9980246-ND</field>
        <field name="Config">DNF</field>
        <field name="Footprint">Connector_PinHeader_2.54mm:PinHeader_2x02_P2.54mm_Vertical</field>
        <field name="Datasheet">~</field>
        <field name="Description">Generic connector, double row, 02x02, odd/even pin numbering scheme (row 1 odd numbers, row 2 even numbers), script generated (kicad-library-utils/schlib/autogen/connector/)</field>
      </fields>
      <libsource lib="Connector_Generic" part="Conn_02x02_Odd_Even" description="Generic connector, double row, 02x02, odd/even pin numbering scheme (row 1 odd numbers, row 2 even numbers), script generated (kicad-library-utils/schlib/autogen/connector/)"/>
      <property name="MFN" value="Harwin Inc."/>
      <property name="MFP" value="M20-9980246-ND"/>
      <property name="Config" value="DNF"/>
      <property name="Sheetname" value="Section A - Title A"/>
      <property name="Sheetfile" value="Section A - Title A.kicad_sch"/>
      <property name="ki_keywords" value="connector"/>
      <property name="ki_fp_filters" value="Connector*:*_2x??_*"/>
      <sheetpath names="/Project Architecture/Section A - Title A/" tstamps="/c5103ceb-5325-4a84-a025-9638a412984e/f06537ee-772d-44d3-8c50-e0ba41038c9c/"/>
      <tstamps>00000000-0000-0000-0000-00005f655b58</tstamps>
    </comp>
    <comp ref="J5">
      <value>ICSP1</value>
      <footprint>Connector_PinHeader_2.54mm:PinHeader_2x03_P2.54mm_Vertical</footprint>
      <datasheet>~</datasheet>
      <description>Generic connector, double row, 02x03, odd/even pin numbering scheme (row 1 odd numbers, row 2 even numbers), script generated (kicad-library-utils/schlib/autogen/connector/)</description>
      <fields>
        <field name="MFN">Harwin Inc.</field>
        <field name="MFP">M20-9980346</field>
        <field name="Config">-USB</field>
        <field name="Footprint">Connector_PinHeader_2.54mm:PinHeader_2x03_P2.54mm_Vertical</field>
        <field name="Datasheet">~</field>
        <field name="Description">Generic connector, double row, 02x03, odd/even pin numbering scheme (row 1 odd numbers, row 2 even numbers), script generated (kicad-library-utils/schlib/autogen/connector/)</field>
      </fields>
      <libsource lib="Connector_Generic" part="Conn_02x03_Odd_Even" description="Generic connector, double row, 02x03, odd/even pin numbering scheme (row 1 odd numbers, row 2 even numbers), script generated (kicad-library-utils/schlib/autogen/connector/)"/>
      <property name="MFN" value="Harwin Inc."/>
      <property name="MFP" value="M20-9980346"/>
      <property name="Config" value="-USB"/>
      <property name="Sheetname" value="Section A - Title A"/>
      <property name="Sheetfile" value="Section A - Title A.kicad_sch"/>
      <property name="ki_keywords" value="connector"/>
      <property name="ki_fp_filters" value="Connector*:*_2x??_*"/>
      <sheetpath names="/Project Architecture/Section A - Title A/" tstamps="/c5103ceb-5325-4a84-a025-9638a412984e/f06537ee-772d-44d3-8c50-e0ba41038c9c/"/>
      <tstamps>00000000-0000-0000-0000-00005f5ee04d</tstamps>
    </comp>
    <comp ref="J6">
      <value>P2</value>
      <footprint>Connector_PinHeader_2.54mm:PinHeader_1x06_P2.54mm_Vertical</footprint>
      <datasheet>~</datasheet>
      <description>Generic connector, single row, 01x06, script generated</description>
      <fields>
        <field name="Footprint">Connector_PinHeader_2.54mm:PinHeader_1x06_P2.54mm_Vertical</field>
        <field name="Datasheet">~</field>
        <field name="Description">Generic connector, single row, 01x06, script generated</field>
      </fields>
      <libsource lib="Connector" part="Conn_01x06_Pin" description="Generic connector, single row, 01x06, script generated"/>
      <property name="Sheetname" value="Section A - Title A"/>
      <property name="Sheetfile" value="Section A - Title A.kicad_sch"/>
      <property name="ki_keywords" value="connector"/>
      <property name="ki_fp_filters" value="Connector*:*_1x??_*"/>
      <sheetpath names="/Project Architecture/Section A - Title A/" tstamps="/c5103ceb-5325-4a84-a025-9638a412984e/f06537ee-772d-44d3-8c50-e0ba41038c9c/"/>
      <tstamps>00000000-0000-0000-0000-00005f71b1a8</tstamps>
    </comp>
    <comp ref="JP1">
      <value>SolderJumper_2_Open</value>
      <footprint>Jumper:SolderJumper-2_P1.3mm_Open_RoundedPad1.0x1.5mm</footprint>
      <datasheet>~</datasheet>
      <description>Solder Jumper, 2-pole, open</description>
      <fields>
        <field name="Footprint">Jumper:SolderJumper-2_P1.3mm_Open_RoundedPad1.0x1.5mm</field>
        <field name="Datasheet">~</field>
        <field name="Description">Solder Jumper, 2-pole, open</field>
      </fields>
      <libsource lib="Jumper" part="SolderJumper_2_Open" description="Solder Jumper, 2-pole, open"/>
      <property name="Sheetname" value="Section A - Title A"/>
      <property name="Sheetfile" value="Section A - Title A.kicad_sch"/>
      <property name="ki_keywords" value="solder jumper SPST"/>
      <property name="ki_fp_filters" value="SolderJumper*Open*"/>
      <sheetpath names="/Project Architecture/Section A - Title A/" tstamps="/c5103ceb-5325-4a84-a025-9638a412984e/f06537ee-772d-44d3-8c50-e0ba41038c9c/"/>
      <tstamps>00000000-0000-0000-0000-00005f5db904</tstamps>
    </comp>
    <comp ref="LOGO1">
      <value>Logo_Open_Hardware_Large</value>
      <footprint>Symbol:OSHW-Logo_11.4x12mm_SilkScreen</footprint>
      <datasheet>~</datasheet>
      <description>Open Hardware logo, large</description>
      <fields>
        <field name="Footprint">Symbol:OSHW-Logo_11.4x12mm_SilkScreen</field>
        <field name="Datasheet">~</field>
        <field name="Description">Open Hardware logo, large</field>
      </fields>
      <libsource lib="Graphic" part="Logo_Open_Hardware_Large" description="Open Hardware logo, large"/>
      <property name="Sheetname" value="Section A - Title A"/>
      <property name="Sheetfile" value="Section A - Title A.kicad_sch"/>
      <property name="ki_keywords" value="Logo"/>
      <sheetpath names="/Project Architecture/Section A - Title A/" tstamps="/c5103ceb-5325-4a84-a025-9638a412984e/f06537ee-772d-44d3-8c50-e0ba41038c9c/"/>
      <tstamps>00000000-0000-0000-0000-00005f85d3c9</tstamps>
    </comp>
    <comp ref="R1">
      <value>22R</value>
      <footprint>Resistor_SMD:R_0805_2012Metric</footprint>
      <datasheet>~</datasheet>
      <description>Resistor</description>
      <fields>
        <field name="Config">+USB</field>
        <field name="Footprint">Resistor_SMD:R_0805_2012Metric</field>
        <field name="Datasheet">~</field>
        <field name="Description">Resistor</field>
      </fields>
      <libsource lib="Device" part="R" description="Resistor"/>
      <property name="Config" value="+USB"/>
      <property name="Sheetname" value="Section A - Title A"/>
      <property name="Sheetfile" value="Section A - Title A.kicad_sch"/>
      <property name="ki_keywords" value="R res resistor"/>
      <property name="ki_fp_filters" value="R_*"/>
      <sheetpath names="/Project Architecture/Section A - Title A/" tstamps="/c5103ceb-5325-4a84-a025-9638a412984e/f06537ee-772d-44d3-8c50-e0ba41038c9c/"/>
      <tstamps>00000000-0000-0000-0000-00005f59f3f0</tstamps>
    </comp>
    <comp ref="R2">
      <value>22R</value>
      <footprint>Resistor_SMD:R_0805_2012Metric</footprint>
      <datasheet>~</datasheet>
      <description>Resistor</description>
      <fields>
        <field name="Config">+USB</field>
        <field name="Footprint">Resistor_SMD:R_0805_2012Metric</field>
        <field name="Datasheet">~</field>
        <field name="Description">Resistor</field>
      </fields>
      <libsource lib="Device" part="R" description="Resistor"/>
      <property name="Config" value="+USB"/>
      <property name="Sheetname" value="Section A - Title A"/>
      <property name="Sheetfile" value="Section A - Title A.kicad_sch"/>
      <property name="ki_keywords" value="R res resistor"/>
      <property name="ki_fp_filters" value="R_*"/>
      <sheetpath names="/Project Architecture/Section A - Title A/" tstamps="/c5103ceb-5325-4a84-a025-9638a412984e/f06537ee-772d-44d3-8c50-e0ba41038c9c/"/>
      <tstamps>00000000-0000-0000-0000-00005f59f9fe</tstamps>
    </comp>
    <comp ref="R3">
      <value>1M</value>
      <footprint>Resistor_SMD:R_0805_2012Metric</footprint>
      <datasheet>~</datasheet>
      <description>Resistor</description>
      <fields>
        <field name="Config">+USB,+XTAL</field>
        <field name="Footprint">Resistor_SMD:R_0805_2012Metric</field>
        <field name="Datasheet">~</field>
        <field name="Description">Resistor</field>
      </fields>
      <libsource lib="Device" part="R" description="Resistor"/>
      <property name="Config" value="+USB,+XTAL"/>
      <property name="Sheetname" value="Section A - Title A"/>
      <property name="Sheetfile" value="Section A - Title A.kicad_sch"/>
      <property name="ki_keywords" value="R res resistor"/>
      <property name="ki_fp_filters" value="R_*"/>
      <sheetpath names="/Project Architecture/Section A - Title A/" tstamps="/c5103ceb-5325-4a84-a025-9638a412984e/f06537ee-772d-44d3-8c50-e0ba41038c9c/"/>
      <tstamps>00000000-0000-0000-0000-00005f58fb32</tstamps>
    </comp>
    <comp ref="R4">
      <value>10K</value>
      <footprint>Resistor_SMD:R_0805_2012Metric</footprint>
      <datasheet>~</datasheet>
      <description>Resistor</description>
      <fields>
        <field name="Footprint">Resistor_SMD:R_0805_2012Metric</field>
        <field name="Datasheet">~</field>
        <field name="Description">Resistor</field>
      </fields>
      <libsource lib="Device" part="R" description="Resistor"/>
      <property name="Sheetname" value="Section A - Title A"/>
      <property name="Sheetfile" value="Section A - Title A.kicad_sch"/>
      <property name="ki_keywords" value="R res resistor"/>
      <property name="ki_fp_filters" value="R_*"/>
      <sheetpath names="/Project Architecture/Section A - Title A/" tstamps="/c5103ceb-5325-4a84-a025-9638a412984e/f06537ee-772d-44d3-8c50-e0ba41038c9c/"/>
      <tstamps>00000000-0000-0000-0000-00005f5e26b1</tstamps>
    </comp>
    <comp ref="R5">
      <value>1K</value>
      <footprint>Resistor_SMD:R_0805_2012Metric</footprint>
      <datasheet>~</datasheet>
      <description>Resistor</description>
      <fields>
        <field name="Footprint">Resistor_SMD:R_0805_2012Metric</field>
        <field name="Datasheet">~</field>
        <field name="Description">Resistor</field>
      </fields>
      <libsource lib="Device" part="R" description="Resistor"/>
      <property name="Sheetname" value="Section A - Title A"/>
      <property name="Sheetfile" value="Section A - Title A.kicad_sch"/>
      <property name="ki_keywords" value="R res resistor"/>
      <property name="ki_fp_filters" value="R_*"/>
      <sheetpath names="/Project Architecture/Section A - Title A/" tstamps="/c5103ceb-5325-4a84-a025-9638a412984e/f06537ee-772d-44d3-8c50-e0ba41038c9c/"/>
      <tstamps>00000000-0000-0000-0000-00005f6f75d3</tstamps>
    </comp>
    <comp ref="R6">
      <value>1K</value>
      <footprint>Resistor_SMD:R_0805_2012Metric</footprint>
      <datasheet>~</datasheet>
      <description>Resistor</description>
      <fields>
        <field name="Footprint">Resistor_SMD:R_0805_2012Metric</field>
        <field name="Datasheet">~</field>
        <field name="Description">Resistor</field>
      </fields>
      <libsource lib="Device" part="R" description="Resistor"/>
      <property name="Sheetname" value="Section A - Title A"/>
      <property name="Sheetfile" value="Section A - Title A.kicad_sch"/>
      <property name="ki_keywords" value="R res resistor"/>
      <property name="ki_fp_filters" value="R_*"/>
      <sheetpath names="/Project Architecture/Section A - Title A/" tstamps="/c5103ceb-5325-4a84-a025-9638a412984e/f06537ee-772d-44d3-8c50-e0ba41038c9c/"/>
      <tstamps>00000000-0000-0000-0000-00005f6c880f</tstamps>
    </comp>
    <comp ref="R7">
      <value>1K</value>
      <footprint>Resistor_SMD:R_0805_2012Metric</footprint>
      <datasheet>~</datasheet>
      <description>Resistor</description>
      <fields>
        <field name="Footprint">Resistor_SMD:R_0805_2012Metric</field>
        <field name="Datasheet">~</field>
        <field name="Description">Resistor</field>
      </fields>
      <libsource lib="Device" part="R" description="Resistor"/>
      <property name="Sheetname" value="Section A - Title A"/>
      <property name="Sheetfile" value="Section A - Title A.kicad_sch"/>
      <property name="ki_keywords" value="R res resistor"/>
      <property name="ki_fp_filters" value="R_*"/>
      <sheetpath names="/Project Architecture/Section A - Title A/" tstamps="/c5103ceb-5325-4a84-a025-9638a412984e/f06537ee-772d-44d3-8c50-e0ba41038c9c/"/>
      <tstamps>00000000-0000-0000-0000-00005f6afc1d</tstamps>
    </comp>
    <comp ref="TP2">
      <value>TestPoint</value>
      <footprint>TestPoint:TestPoint_Pad_D1.0mm</footprint>
      <datasheet>~</datasheet>
      <description>test point</description>
      <fields>
        <field name="Footprint">TestPoint:TestPoint_Pad_D1.0mm</field>
        <field name="Datasheet">~</field>
        <field name="Description">test point</field>
      </fields>
      <libsource lib="Connector" part="TestPoint" description="test point"/>
      <property name="Sheetname" value="Section A - Title A"/>
      <property name="Sheetfile" value="Section A - Title A.kicad_sch"/>
      <property name="ki_keywords" value="test point tp"/>
      <property name="ki_fp_filters" value="Pin* Test*"/>
      <sheetpath names="/Project Architecture/Section A - Title A/" tstamps="/c5103ceb-5325-4a84-a025-9638a412984e/f06537ee-772d-44d3-8c50-e0ba41038c9c/"/>
      <tstamps>00000000-0000-0000-0000-00005f5b39e3</tstamps>
    </comp>
    <comp ref="TP3">
      <value>TestPoint</value>
      <footprint>TestPoint:TestPoint_Pad_D1.0mm</footprint>
      <datasheet>~</datasheet>
      <description>test point</description>
      <fields>
        <field name="Footprint">TestPoint:TestPoint_Pad_D1.0mm</field>
        <field name="Datasheet">~</field>
        <field name="Description">test point</field>
      </fields>
      <libsource lib="Connector" part="TestPoint" description="test point"/>
      <property name="Sheetname" value="Section A - Title A"/>
      <property name="Sheetfile" value="Section A - Title A.kicad_sch"/>
      <property name="ki_keywords" value="test point tp"/>
      <property name="ki_fp_filters" value="Pin* Test*"/>
      <sheetpath names="/Project Architecture/Section A - Title A/" tstamps="/c5103ceb-5325-4a84-a025-9638a412984e/f06537ee-772d-44d3-8c50-e0ba41038c9c/"/>
      <tstamps>00000000-0000-0000-0000-00005f5d16b6</tstamps>
    </comp>
    <comp ref="TP4">
      <value>TestPoint</value>
      <footprint>TestPoint:TestPoint_Pad_D1.0mm</footprint>
      <datasheet>~</datasheet>
      <description>test point</description>
      <fields>
        <field name="Footprint">TestPoint:TestPoint_Pad_D1.0mm</field>
        <field name="Datasheet">~</field>
        <field name="Description">test point</field>
      </fields>
      <libsource lib="Connector" part="TestPoint" description="test point"/>
      <property name="Sheetname" value="Section A - Title A"/>
      <property name="Sheetfile" value="Section A - Title A.kicad_sch"/>
      <property name="ki_keywords" value="test point tp"/>
      <property name="ki_fp_filters" value="Pin* Test*"/>
      <sheetpath names="/Project Architecture/Section A - Title A/" tstamps="/c5103ceb-5325-4a84-a025-9638a412984e/f06537ee-772d-44d3-8c50-e0ba41038c9c/"/>
      <tstamps>00000000-0000-0000-0000-00005f5b7e09</tstamps>
    </comp>
    <comp ref="TP5">
      <value>TestPoint</value>
      <footprint>TestPoint:TestPoint_Pad_D1.0mm</footprint>
      <datasheet>~</datasheet>
      <description>test point</description>
      <fields>
        <field name="Footprint">TestPoint:TestPoint_Pad_D1.0mm</field>
        <field name="Datasheet">~</field>
        <field name="Description">test point</field>
      </fields>
      <libsource lib="Connector" part="TestPoint" description="test point"/>
      <property name="Sheetname" value="Section A - Title A"/>
      <property name="Sheetfile" value="Section A - Title A.kicad_sch"/>
      <property name="ki_keywords" value="test point tp"/>
      <property name="ki_fp_filters" value="Pin* Test*"/>
      <sheetpath names="/Project Architecture/Section A - Title A/" tstamps="/c5103ceb-5325-4a84-a025-9638a412984e/f06537ee-772d-44d3-8c50-e0ba41038c9c/"/>
      <tstamps>00000000-0000-0000-0000-00005f5acb0e</tstamps>
    </comp>
    <comp ref="TP6">
      <value>TestPoint</value>
      <footprint>TestPoint:TestPoint_Pad_D1.0mm</footprint>
      <datasheet>~</datasheet>
      <description>test point</description>
      <fields>
        <field name="Footprint">TestPoint:TestPoint_Pad_D1.0mm</field>
        <field name="Datasheet">~</field>
        <field name="Description">test point</field>
      </fields>
      <libsource lib="Connector" part="TestPoint" description="test point"/>
      <property name="Sheetname" value="Section A - Title A"/>
      <property name="Sheetfile" value="Section A - Title A.kicad_sch"/>
      <property name="ki_keywords" value="test point tp"/>
      <property name="ki_fp_filters" value="Pin* Test*"/>
      <sheetpath names="/Project Architecture/Section A - Title A/" tstamps="/c5103ceb-5325-4a84-a025-9638a412984e/f06537ee-772d-44d3-8c50-e0ba41038c9c/"/>
      <tstamps>00000000-0000-0000-0000-00005f594e26</tstamps>
    </comp>
    <comp ref="TP8">
      <value>TestPoint</value>
      <footprint>TestPoint:TestPoint_Pad_D1.0mm</footprint>
      <datasheet>~</datasheet>
      <description>test point</description>
      <fields>
        <field name="Footprint">TestPoint:TestPoint_Pad_D1.0mm</field>
        <field name="Datasheet">~</field>
        <field name="Description">test point</field>
      </fields>
      <libsource lib="Connector" part="TestPoint" description="test point"/>
      <property name="Sheetname" value="Section A - Title A"/>
      <property name="Sheetfile" value="Section A - Title A.kicad_sch"/>
      <property name="ki_keywords" value="test point tp"/>
      <property name="ki_fp_filters" value="Pin* Test*"/>
      <sheetpath names="/Project Architecture/Section A - Title A/" tstamps="/c5103ceb-5325-4a84-a025-9638a412984e/f06537ee-772d-44d3-8c50-e0ba41038c9c/"/>
      <tstamps>00000000-0000-0000-0000-00005f5964e4</tstamps>
    </comp>
    <comp ref="TP9">
      <value>TestPoint</value>
      <footprint>TestPoint:TestPoint_Pad_D1.0mm</footprint>
      <datasheet>~</datasheet>
      <description>test point</description>
      <fields>
        <field name="Footprint">TestPoint:TestPoint_Pad_D1.0mm</field>
        <field name="Datasheet">~</field>
        <field name="Description">test point</field>
      </fields>
      <libsource lib="Connector" part="TestPoint" description="test point"/>
      <property name="Sheetname" value="Section A - Title A"/>
      <property name="Sheetfile" value="Section A - Title A.kicad_sch"/>
      <property name="ki_keywords" value="test point tp"/>
      <property name="ki_fp_filters" value="Pin* Test*"/>
      <sheetpath names="/Project Architecture/Section A - Title A/" tstamps="/c5103ceb-5325-4a84-a025-9638a412984e/f06537ee-772d-44d3-8c50-e0ba41038c9c/"/>
      <tstamps>00000000-0000-0000-0000-00005f5ae56c</tstamps>
    </comp>
    <comp ref="U1">
      <value>ATmega8U2-AU</value>
      <footprint>Package_QFP:TQFP-32_7x7mm_P0.8mm</footprint>
      <datasheet>http://ww1.microchip.com/downloads/en/DeviceDoc/doc7799.pdf</datasheet>
      <description>16MHz, 8kB Flash, 512B SRAM, 512B EEPROM, TQFP-32</description>
      <fields>
        <field name="Footprint">Package_QFP:TQFP-32_7x7mm_P0.8mm</field>
        <field name="Datasheet">http://ww1.microchip.com/downloads/en/DeviceDoc/doc7799.pdf</field>
        <field name="Description">16MHz, 8kB Flash, 512B SRAM, 512B EEPROM, TQFP-32</field>
      </fields>
      <libsource lib="MCU_Microchip_ATmega" part="ATmega8U2-A" description="16MHz, 8kB Flash, 512B SRAM, 512B EEPROM, TQFP-32"/>
      <property name="Sheetname" value="Section A - Title A"/>
      <property name="Sheetfile" value="Section A - Title A.kicad_sch"/>
      <property name="ki_keywords" value="AVR 8bit Microcontroller MegaAVR"/>
      <property name="ki_fp_filters" value="TQFP*7x7mm*P0.8mm*"/>
      <sheetpath names="/Project Architecture/Section A - Title A/" tstamps="/c5103ceb-5325-4a84-a025-9638a412984e/f06537ee-772d-44d3-8c50-e0ba41038c9c/"/>
      <tstamps>00000000-0000-0000-0000-00005f58d91d</tstamps>
    </comp>
    <comp ref="VR1">
      <value>CG0603MLC-05E</value>
      <footprint>Resistor_SMD:R_0603_1608Metric</footprint>
      <datasheet>~</datasheet>
      <description>Voltage dependent resistor</description>
      <fields>
        <field name="MFN">Bourns Inc.</field>
        <field name="MFP">CG0603MLC-05E</field>
        <field name="Config">+USB</field>
        <field name="Sim.Name">kicad_builtin_varistor</field>
        <field name="Sim.Device">SUBCKT</field>
        <field name="Sim.Pins">1=A 2=B</field>
        <field name="Sim.Params">threshold=1k</field>
        <field name="Sim.Library">${KICAD7_SYMBOL_DIR}/Simulation_SPICE.sp</field>
        <field name="Footprint">Resistor_SMD:R_0603_1608Metric</field>
        <field name="Datasheet">~</field>
        <field name="Description">Voltage dependent resistor</field>
      </fields>
      <libsource lib="Device" part="Varistor" description="Voltage dependent resistor"/>
      <property name="MFN" value="Bourns Inc."/>
      <property name="MFP" value="CG0603MLC-05E"/>
      <property name="Config" value="+USB"/>
      <property name="Sim.Name" value="kicad_builtin_varistor"/>
      <property name="Sim.Device" value="SUBCKT"/>
      <property name="Sim.Pins" value="1=A 2=B"/>
      <property name="Sim.Params" value="threshold=1k"/>
      <property name="Sim.Library" value="${KICAD7_SYMBOL_DIR}/Simulation_SPICE.sp"/>
      <property name="Sheetname" value="Section A - Title A"/>
      <property name="Sheetfile" value="Section A - Title A.kicad_sch"/>
      <property name="ki_keywords" value="VDR resistance"/>
      <property name="ki_fp_filters" value="RV_* Varistor*"/>
      <sheetpath names="/Project Architecture/Section A - Title A/" tstamps="/c5103ceb-5325-4a84-a025-9638a412984e/f06537ee-772d-44d3-8c50-e0ba41038c9c/"/>
      <tstamps>00000000-0000-0000-0000-00005f5a461f</tstamps>
    </comp>
    <comp ref="VR2">
      <value>CG0603MLC-05E</value>
      <footprint>Resistor_SMD:R_0603_1608Metric</footprint>
      <datasheet>~</datasheet>
      <description>Voltage dependent resistor</description>
      <fields>
        <field name="MFN">Bourns Inc.</field>
        <field name="MFP">CG0603MLC-05E</field>
        <field name="Config">+USB</field>
        <field name="Sim.Name">kicad_builtin_varistor</field>
        <field name="Sim.Device">SUBCKT</field>
        <field name="Sim.Pins">1=A 2=B</field>
        <field name="Sim.Params">threshold=1k</field>
        <field name="Sim.Library">${KICAD7_SYMBOL_DIR}/Simulation_SPICE.sp</field>
        <field name="Footprint">Resistor_SMD:R_0603_1608Metric</field>
        <field name="Datasheet">~</field>
        <field name="Description">Voltage dependent resistor</field>
      </fields>
      <libsource lib="Device" part="Varistor" description="Voltage dependent resistor"/>
      <property name="MFN" value="Bourns Inc."/>
      <property name="MFP" value="CG0603MLC-05E"/>
      <property name="Config" value="+USB"/>
      <property name="Sim.Name" value="kicad_builtin_varistor"/>
      <property name="Sim.Device" value="SUBCKT"/>
      <property name="Sim.Pins" value="1=A 2=B"/>
      <property name="Sim.Params" value="threshold=1k"/>
      <property name="Sim.Library" value="${KICAD7_SYMBOL_DIR}/Simulation_SPICE.sp"/>
      <property name="Sheetname" value="Section A - Title A"/>
      <property name="Sheetfile" value="Section A - Title A.kicad_sch"/>
      <property name="ki_keywords" value="VDR resistance"/>
      <property name="ki_fp_filters" value="RV_* Varistor*"/>
      <sheetpath names="/Project Architecture/Section A - Title A/" tstamps="/c5103ceb-5325-4a84-a025-9638a412984e/f06537ee-772d-44d3-8c50-e0ba41038c9c/"/>
      <tstamps>00000000-0000-0000-0000-00005f596a91</tstamps>
    </comp>
    <comp ref="Y1">
      <value>16MHz</value>
      <footprint>Crystal:Crystal_SMD_Abracon_ABM3-2Pin_5.0x3.2mm</footprint>
      <datasheet>~</datasheet>
      <description>Two pin crystal</description>
      <fields>
        <field name="MFN">Abracon LLC</field>
        <field name="MFP">ABM3-16.000MHZ-B2-T</field>
        <field name="Config">+USB,+XTAL</field>
        <field name="Footprint">Crystal:Crystal_SMD_Abracon_ABM3-2Pin_5.0x3.2mm</field>
        <field name="Datasheet">~</field>
        <field name="Description">Two pin crystal</field>
      </fields>
      <libsource lib="Device" part="Crystal" description="Two pin crystal"/>
      <property name="MFN" value="Abracon LLC"/>
      <property name="MFP" value="ABM3-16.000MHZ-B2-T"/>
      <property name="Config" value="+USB,+XTAL"/>
      <property name="Sheetname" value="Section A - Title A"/>
      <property name="Sheetfile" value="Section A - Title A.kicad_sch"/>
      <property name="ki_keywords" value="quartz ceramic resonator oscillator"/>
      <property name="ki_fp_filters" value="Crystal*"/>
      <sheetpath names="/Project Architecture/Section A - Title A/" tstamps="/c5103ceb-5325-4a84-a025-9638a412984e/f06537ee-772d-44d3-8c50-e0ba41038c9c/"/>
      <tstamps>00000000-0000-0000-0000-00005f598bfc</tstamps>
    </comp>
  </components>
  <libparts>
    <libpart lib="Connector" part="Barrel_Jack_Switch">
      <description>DC Barrel Jack with an internal switch</description>
      <docs>~</docs>
      <footprints>
        <fp>BarrelJack*</fp>
      </footprints>
      <fields>
        <field name="Reference">J</field>
        <field name="Value">Barrel_Jack_Switch</field>
        <field name="Footprint"/>
        <field name="Datasheet">~</field>
        <field name="Description">DC Barrel Jack with an internal switch</field>
      </fields>
      <pins>
        <pin num="1" name="" type="passive"/>
        <pin num="2" name="" type="passive"/>
        <pin num="3" name="" type="passive"/>
      </pins>
    </libpart>
    <libpart lib="Connector" part="Conn_01x05_Pin">
      <description>Generic connector, single row, 01x05, script generated</description>
      <docs>~</docs>
      <footprints>
        <fp>Connector*:*_1x??_*</fp>
      </footprints>
      <fields>
        <field name="Reference">J</field>
        <field name="Value">Conn_01x05_Pin</field>
        <field name="Footprint"/>
        <field name="Datasheet">~</field>
        <field name="Description">Generic connector, single row, 01x05, script generated</field>
      </fields>
      <pins>
        <pin num="1" name="Pin_1" type="passive"/>
        <pin num="2" name="Pin_2" type="passive"/>
        <pin num="3" name="Pin_3" type="passive"/>
        <pin num="4" name="Pin_4" type="passive"/>
        <pin num="5" name="Pin_5" type="passive"/>
      </pins>
    </libpart>
    <libpart lib="Connector" part="Conn_01x06_Pin">
      <description>Generic connector, single row, 01x06, script generated</description>
      <docs>~</docs>
      <footprints>
        <fp>Connector*:*_1x??_*</fp>
      </footprints>
      <fields>
        <field name="Reference">J</field>
        <field name="Value">Conn_01x06_Pin</field>
        <field name="Footprint"/>
        <field name="Datasheet">~</field>
        <field name="Description">Generic connector, single row, 01x06, script generated</field>
      </fields>
      <pins>
        <pin num="1" name="Pin_1" type="passive"/>
        <pin num="2" name="Pin_2" type="passive"/>
        <pin num="3" name="Pin_3" type="passive"/>
        <pin num="4" name="Pin_4" type="passive"/>
        <pin num="5" name="Pin_5" type="passive"/>
        <pin num="6" name="Pin_6" type="passive"/>
      </pins>
    </libpart>
    <libpart lib="Connector" part="TestPoint">
      <description>test point</description>
      <docs>~</docs>
      <footprints>
        <fp>Pin*</fp>
        <fp>Test*</fp>
      </footprints>
      <fields>
        <field name="Reference">TP</field>
        <field name="Value">TestPoint</field>
        <field name="Footprint"/>
        <field name="Datasheet">~</field>
        <field name="Description">test point</field>
      </fields>
      <pins>
        <pin num="1" name="1" type="passive"/>
      </pins>
    </libpart>
    <libpart lib="Connector" part="USB_B">
      <description>USB Type B connector</description>
      <docs>~</docs>
      <footprints>
        <fp>USB*</fp>
      </footprints>
      <fields>
        <field name="Reference">J</field>
        <field name="Value">USB_B</field>
        <field name="Footprint"/>
        <field name="Datasheet">~</field>
        <field name="Description">USB Type B connector</field>
      </fields>
      <pins>
        <pin num="1" name="VBUS" type="power_out"/>
        <pin num="2" name="D-" type="bidirectional"/>
        <pin num="3" name="D+" type="bidirectional"/>
        <pin num="4" name="GND" type="power_out"/>
        <pin num="5" name="Shield" type="passive"/>
      </pins>
    </libpart>
    <libpart lib="Connector_Generic" part="Conn_02x02_Odd_Even">
      <description>Generic connector, double row, 02x02, odd/even pin numbering scheme (row 1 odd numbers, row 2 even numbers), script generated (kicad-library-utils/schlib/autogen/connector/)</description>
      <docs>~</docs>
      <footprints>
        <fp>Connector*:*_2x??_*</fp>
      </footprints>
      <fields>
        <field name="Reference">J</field>
        <field name="Value">Conn_02x02_Odd_Even</field>
        <field name="Footprint"/>
        <field name="Datasheet">~</field>
        <field name="Description">Generic connector, double row, 02x02, odd/even pin numbering scheme (row 1 odd numbers, row 2 even numbers), script generated (kicad-library-utils/schlib/autogen/connector/)</field>
      </fields>
      <pins>
        <pin num="1" name="Pin_1" type="passive"/>
        <pin num="2" name="Pin_2" type="passive"/>
        <pin num="3" name="Pin_3" type="passive"/>
        <pin num="4" name="Pin_4" type="passive"/>
      </pins>
    </libpart>
    <libpart lib="Connector_Generic" part="Conn_02x03_Odd_Even">
      <description>Generic connector, double row, 02x03, odd/even pin numbering scheme (row 1 odd numbers, row 2 even numbers), script generated (kicad-library-utils/schlib/autogen/connector/)</description>
      <docs>~</docs>
      <footprints>
        <fp>Connector*:*_2x??_*</fp>
      </footprints>
      <fields>
        <field name="Reference">J</field>
        <field name="Value">Conn_02x03_Odd_Even</field>
        <field name="Footprint"/>
        <field name="Datasheet">~</field>
        <field name="Description">Generic connector, double row, 02x03, odd/even pin numbering scheme (row 1 odd numbers, row 2 even numbers), script generated (kicad-library-utils/schlib/autogen/connector/)</field>
      </fields>
      <pins>
        <pin num="1" name="Pin_1" type="passive"/>
        <pin num="2" name="Pin_2" type="passive"/>
        <pin num="3" name="Pin_3" type="passive"/>
        <pin num="4" name="Pin_4" type="passive"/>
        <pin num="5" name="Pin_5" type="passive"/>
        <pin num="6" name="Pin_6" type="passive"/>
      </pins>
    </libpart>
    <libpart lib="Device" part="C">
      <description>Unpolarized capacitor</description>
      <docs>~</docs>
      <footprints>
        <fp>C_*</fp>
      </footprints>
      <fields>
        <field name="Reference">C</field>
        <field name="Value">C</field>
        <field name="Footprint"/>
        <field name="Datasheet">~</field>
        <field name="Description">Unpolarized capacitor</field>
      </fields>
      <pins>
        <pin num="1" name="" type="passive"/>
        <pin num="2" name="" type="passive"/>
      </pins>
    </libpart>
    <libpart lib="Device" part="C_Polarized">
      <description>Polarized capacitor</description>
      <docs>~</docs>
      <footprints>
        <fp>CP_*</fp>
      </footprints>
      <fields>
        <field name="Reference">C</field>
        <field name="Value">C_Polarized</field>
        <field name="Footprint"/>
        <field name="Datasheet">~</field>
        <field name="Description">Polarized capacitor</field>
      </fields>
      <pins>
        <pin num="1" name="" type="passive"/>
        <pin num="2" name="" type="passive"/>
      </pins>
    </libpart>
    <libpart lib="Device" part="Crystal">
      <description>Two pin crystal</description>
      <docs>~</docs>
      <footprints>
        <fp>Crystal*</fp>
      </footprints>
      <fields>
        <field name="Reference">Y</field>
        <field name="Value">Crystal</field>
        <field name="Footprint"/>
        <field name="Datasheet">~</field>
        <field name="Description">Two pin crystal</field>
      </fields>
      <pins>
        <pin num="1" name="1" type="passive"/>
        <pin num="2" name="2" type="passive"/>
      </pins>
    </libpart>
    <libpart lib="Device" part="D">
      <description>Diode</description>
      <docs>~</docs>
      <footprints>
        <fp>TO-???*</fp>
        <fp>*_Diode_*</fp>
        <fp>*SingleDiode*</fp>
        <fp>D_*</fp>
      </footprints>
      <fields>
        <field name="Reference">D</field>
        <field name="Value">D</field>
        <field name="Footprint"/>
        <field name="Datasheet">~</field>
        <field name="Description">Diode</field>
        <field name="Sim.Device">D</field>
        <field name="Sim.Pins">1=K 2=A</field>
      </fields>
      <pins>
        <pin num="1" name="K" type="passive"/>
        <pin num="2" name="A" type="passive"/>
      </pins>
    </libpart>
    <libpart lib="Device" part="FerriteBead">
      <description>Ferrite bead</description>
      <docs>~</docs>
      <footprints>
        <fp>Inductor_*</fp>
        <fp>L_*</fp>
        <fp>*Ferrite*</fp>
      </footprints>
      <fields>
        <field name="Reference">FB</field>
        <field name="Value">FerriteBead</field>
        <field name="Footprint"/>
        <field name="Datasheet">~</field>
        <field name="Description">Ferrite bead</field>
      </fields>
      <pins>
        <pin num="1" name="" type="passive"/>
        <pin num="2" name="" type="passive"/>
      </pins>
    </libpart>
    <libpart lib="Device" part="LED">
      <description>Light emitting diode</description>
      <docs>~</docs>
      <footprints>
        <fp>LED*</fp>
        <fp>LED_SMD:*</fp>
        <fp>LED_THT:*</fp>
      </footprints>
      <fields>
        <field name="Reference">D</field>
        <field name="Value">LED</field>
        <field name="Footprint"/>
        <field name="Datasheet">~</field>
        <field name="Description">Light emitting diode</field>
        <field name="Sim.Pins">1=K 2=A</field>
      </fields>
      <pins>
        <pin num="1" name="K" type="passive"/>
        <pin num="2" name="A" type="passive"/>
      </pins>
    </libpart>
    <libpart lib="Device" part="Polyfuse">
      <description>Resettable fuse, polymeric positive temperature coefficient</description>
      <docs>~</docs>
      <footprints>
        <fp>*polyfuse*</fp>
        <fp>*PTC*</fp>
      </footprints>
      <fields>
        <field name="Reference">F</field>
        <field name="Value">Polyfuse</field>
        <field name="Footprint"/>
        <field name="Datasheet">~</field>
        <field name="Description">Resettable fuse, polymeric positive temperature coefficient</field>
      </fields>
      <pins>
        <pin num="1" name="" type="passive"/>
        <pin num="2" name="" type="passive"/>
      </pins>
    </libpart>
    <libpart lib="Device" part="R">
      <description>Resistor</description>
      <docs>~</docs>
      <footprints>
        <fp>R_*</fp>
      </footprints>
      <fields>
        <field name="Reference">R</field>
        <field name="Value">R</field>
        <field name="Footprint"/>
        <field name="Datasheet">~</field>
        <field name="Description">Resistor</field>
      </fields>
      <pins>
        <pin num="1" name="" type="passive"/>
        <pin num="2" name="" type="passive"/>
      </pins>
    </libpart>
    <libpart lib="Device" part="Varistor">
      <description>Voltage dependent resistor</description>
      <docs>~</docs>
      <footprints>
        <fp>RV_*</fp>
        <fp>Varistor*</fp>
      </footprints>
      <fields>
        <field name="Reference">RV</field>
        <field name="Value">Varistor</field>
        <field name="Footprint"/>
        <field name="Datasheet">~</field>
        <field name="Description">Voltage dependent resistor</field>
        <field name="Sim.Name">kicad_builtin_varistor</field>
        <field name="Sim.Device">SUBCKT</field>
        <field name="Sim.Pins">1=A 2=B</field>
        <field name="Sim.Params">threshold=1k</field>
        <field name="Sim.Library">${KICAD7_SYMBOL_DIR}/Simulation_SPICE.sp</field>
      </fields>
      <pins>
        <pin num="1" name="" type="passive"/>
        <pin num="2" name="" type="passive"/>
      </pins>
    </libpart>
    <libpart lib="Graphic" part="Logo_Open_Hardware_Large">
      <description>Open Hardware logo, large</description>
      <docs>~</docs>
      <fields>
        <field name="Reference">#SYM</field>
        <field name="Value">Logo_Open_Hardware_Large</field>
        <field name="Footprint"/>
        <field name="Datasheet">~</field>
        <field name="Description">Open Hardware logo, large</field>
        <field name="Sim.Enable">0</field>
      </fields>
    </libpart>
    <libpart lib="Jumper" part="SolderJumper_2_Open">
      <description>Solder Jumper, 2-pole, open</description>
      <docs>~</docs>
      <footprints>
        <fp>SolderJumper*Open*</fp>
      </footprints>
      <fields>
        <field name="Reference">JP</field>
        <field name="Value">SolderJumper_2_Open</field>
        <field name="Footprint"/>
        <field name="Datasheet">~</field>
        <field name="Description">Solder Jumper, 2-pole, open</field>
      </fields>
      <pins>
        <pin num="1" name="A" type="passive"/>
        <pin num="2" name="B" type="passive"/>
      </pins>
    </libpart>
    <libpart lib="MCU_Microchip_ATmega" part="ATmega8U2-A">
      <description>16MHz, 8kB Flash, 512B SRAM, 512B EEPROM, TQFP-32</description>
      <docs>http://ww1.microchip.com/downloads/en/DeviceDoc/doc7799.pdf</docs>
      <footprints>
        <fp>TQFP*7x7mm*P0.8mm*</fp>
      </footprints>
      <fields>
        <field name="Reference">U</field>
        <field name="Value">ATmega8U2-A</field>
        <field name="Footprint">Package_QFP:TQFP-32_7x7mm_P0.8mm</field>
        <field name="Datasheet">http://ww1.microchip.com/downloads/en/DeviceDoc/doc7799.pdf</field>
        <field name="Description">16MHz, 8kB Flash, 512B SRAM, 512B EEPROM, TQFP-32</field>
      </fields>
      <pins>
        <pin num="1" name="XTAL1" type="input"/>
        <pin num="2" name="PC0/XTAL2" type="bidirectional"/>
        <pin num="3" name="GND" type="power_in"/>
        <pin num="4" name="VCC" type="power_in"/>
        <pin num="5" name="PC2" type="bidirectional"/>
        <pin num="6" name="PD0" type="bidirectional"/>
        <pin num="7" name="PD1" type="bidirectional"/>
        <pin num="8" name="PD2" type="bidirectional"/>
        <pin num="9" name="PD3" type="bidirectional"/>
        <pin num="10" name="PD4" type="bidirectional"/>
        <pin num="11" name="PD5" type="bidirectional"/>
        <pin num="12" name="PD6" type="bidirectional"/>
        <pin num="13" name="~{HWB}/PD7" type="bidirectional"/>
        <pin num="14" name="PB0" type="bidirectional"/>
        <pin num="15" name="PB1" type="bidirectional"/>
        <pin num="16" name="PB2" type="bidirectional"/>
        <pin num="17" name="PB3" type="bidirectional"/>
        <pin num="18" name="PB4" type="bidirectional"/>
        <pin num="19" name="PB5" type="bidirectional"/>
        <pin num="20" name="PB6" type="bidirectional"/>
        <pin num="21" name="PB7" type="bidirectional"/>
        <pin num="22" name="PC7" type="bidirectional"/>
        <pin num="23" name="PC6" type="bidirectional"/>
        <pin num="24" name="PC1/~{RESET}" type="bidirectional"/>
        <pin num="25" name="PC5" type="bidirectional"/>
        <pin num="26" name="PC4" type="bidirectional"/>
        <pin num="27" name="UCAP" type="passive"/>
        <pin num="28" name="UGND" type="power_in"/>
        <pin num="29" name="D+" type="bidirectional"/>
        <pin num="30" name="D-" type="bidirectional"/>
        <pin num="31" name="UVCC" type="power_in"/>
        <pin num="32" name="AVCC" type="power_in"/>
      </pins>
    </libpart>
    <libpart lib="Mechanical" part="Fiducial">
      <description>Fiducial Marker</description>
      <docs>~</docs>
      <footprints>
        <fp>Fiducial*</fp>
      </footprints>
      <fields>
        <field name="Reference">FID</field>
        <field name="Value">Fiducial</field>
        <field name="Footprint"/>
        <field name="Datasheet">~</field>
        <field name="Description">Fiducial Marker</field>
      </fields>
    </libpart>
    <libpart lib="Mechanical" part="MountingHole">
      <description>Mounting Hole without connection</description>
      <docs>~</docs>
      <footprints>
        <fp>MountingHole*</fp>
      </footprints>
      <fields>
        <field name="Reference">H</field>
        <field name="Value">MountingHole</field>
        <field name="Footprint"/>
        <field name="Datasheet">~</field>
        <field name="Description">Mounting Hole without connection</field>
      </fields>
    </libpart>
  </libparts>
  <libraries>
    <library logical="Connector">
      <uri>/usr/share/kicad/symbols//Connector.kicad_sym</uri>
    </library>
    <library logical="Connector_Generic">
      <uri>/usr/share/kicad/symbols//Connector_Generic.kicad_sym</uri>
    </library>
    <library logical="Device">
      <uri>/usr/share/kicad/symbols//Device.kicad_sym</uri>
    </library>
    <library logical="Graphic">
      <uri>/usr/share/kicad/symbols//Graphic.kicad_sym</uri>
    </library>
    <library logical="Jumper">
      <uri>/usr/share/kicad/symbols//Jumper.kicad_sym</uri>
    </library>
    <library logical="MCU_Microchip_ATmega">
      <uri>/usr/share/kicad/symbols//MCU_Microchip_ATmega.kicad_sym</uri>
    </library>
    <library logical="Mechanical">
      <uri>/usr/share/kicad/symbols//Mechanical.kicad_sym</uri>
    </library>
  </libraries>
  <nets>
    <net code="1" name="+5V" class="Default">
      <node ref="C1" pin="1" pintype="passive"/>
      <node ref="C2" pin="1" pintype="passive"/>
      <node ref="C7" pin="1" pintype="passive"/>
      <node ref="D1" pin="1" pinfunction="K" pintype="passive"/>
      <node ref="J1" pin="2" pintype="passive"/>
      <node ref="J1" pin="3" pintype="passive"/>
      <node ref="J5" pin="2" pinfunction="Pin_2" pintype="passive"/>
      <node ref="R4" pin="1" pintype="passive"/>
      <node ref="R6" pin="1" pintype="passive"/>
      <node ref="R7" pin="1" pintype="passive"/>
      <node ref="U1" pin="32" pinfunction="AVCC" pintype="power_in"/>
      <node ref="U1" pin="4" pinfunction="VCC" pintype="power_in"/>
    </net>
    <net code="2" name="/Project Architecture/Section A - Title A/DTR" class="Default">
      <node ref="C8" pin="1" pintype="passive"/>
      <node ref="R5" pin="1" pintype="passive"/>
      <node ref="U1" pin="13" pinfunction="~{HWB}/PD7" pintype="bidirectional"/>
    </net>
    <net code="3" name="/Project Architecture/Section A - Title A/MISO2" class="Default">
      <node ref="J5" pin="1" pinfunction="Pin_1" pintype="passive"/>
      <node ref="U1" pin="17" pinfunction="PB3" pintype="bidirectional"/>
    </net>
    <net code="4" name="/Project Architecture/Section A - Title A/MOSI2" class="Default">
      <node ref="J5" pin="4" pinfunction="Pin_4" pintype="passive"/>
      <node ref="U1" pin="16" pinfunction="PB2" pintype="bidirectional"/>
    </net>
    <net code="5" name="/Project Architecture/Section A - Title A/RESET2" class="Default">
      <node ref="D1" pin="2" pinfunction="A" pintype="passive"/>
      <node ref="J5" pin="5" pinfunction="Pin_5" pintype="passive"/>
      <node ref="R4" pin="2" pintype="passive"/>
      <node ref="U1" pin="24" pinfunction="PC1/~{RESET}" pintype="bidirectional"/>
    </net>
    <net code="6" name="/Project Architecture/Section A - Title A/RXLED" class="Default">
      <node ref="D2" pin="1" pinfunction="K" pintype="passive"/>
      <node ref="U1" pin="10" pinfunction="PD4" pintype="bidirectional"/>
    </net>
    <net code="7" name="/Project Architecture/Section A - Title A/SCK2" class="Default">
      <node ref="J5" pin="3" pinfunction="Pin_3" pintype="passive"/>
      <node ref="U1" pin="15" pinfunction="PB1" pintype="bidirectional"/>
    </net>
    <net code="8" name="/Project Architecture/Section A - Title A/TXLED" class="Default">
      <node ref="D3" pin="1" pinfunction="K" pintype="passive"/>
      <node ref="U1" pin="11" pinfunction="PD5" pintype="bidirectional"/>
    </net>
    <net code="9" name="Earth" class="Default">
      <node ref="C5" pin="2" pintype="passive"/>
      <node ref="C6" pin="2" pintype="passive"/>
      <node ref="FB1" pin="2" pintype="passive"/>
      <node ref="J2" pin="4" pinfunction="GND" pintype="power_out"/>
      <node ref="JP1" pin="1" pinfunction="A" pintype="passive"/>
      <node ref="TP4" pin="1" pinfunction="1" pintype="passive"/>
      <node ref="U1" pin="28" pinfunction="UGND" pintype="power_in"/>
    </net>
    <net code="10" name="GND" class="Default">
      <node ref="C1" pin="2" pintype="passive"/>
      <node ref="C2" pin="2" pintype="passive"/>
      <node ref="C3" pin="2" pintype="passive"/>
      <node ref="C4" pin="2" pintype="passive"/>
      <node ref="C7" pin="2" pintype="passive"/>
      <node ref="J1" pin="1" pintype="passive"/>
      <node ref="J5" pin="6" pinfunction="Pin_6" pintype="passive"/>
      <node ref="JP1" pin="2" pinfunction="B" pintype="passive"/>
      <node ref="R5" pin="2" pintype="passive"/>
      <node ref="U1" pin="3" pinfunction="GND" pintype="power_in"/>
    </net>
    <net code="11" name="Net-(D2-A)" class="Default">
      <node ref="D2" pin="2" pinfunction="A" pintype="passive"/>
      <node ref="R6" pin="2" pintype="passive"/>
    </net>
    <net code="12" name="Net-(D3-A)" class="Default">
      <node ref="D3" pin="2" pinfunction="A" pintype="passive"/>
      <node ref="R7" pin="2" pintype="passive"/>
    </net>
    <net code="13" name="Net-(J2-D+)" class="Default">
      <node ref="J2" pin="3" pinfunction="D+" pintype="bidirectional"/>
      <node ref="R1" pin="2" pintype="passive"/>
      <node ref="TP5" pin="1" pinfunction="1" pintype="passive"/>
      <node ref="VR1" pin="1" pintype="passive"/>
    </net>
    <net code="14" name="Net-(J2-D-)" class="Default">
      <node ref="J2" pin="2" pinfunction="D-" pintype="bidirectional"/>
      <node ref="R2" pin="2" pintype="passive"/>
      <node ref="VR2" pin="1" pintype="passive"/>
    </net>
    <net code="15" name="Net-(J2-Shield)" class="Default">
      <node ref="FB1" pin="1" pintype="passive"/>
      <node ref="J2" pin="5" pinfunction="Shield" pintype="passive"/>
      <node ref="VR1" pin="2" pintype="passive"/>
      <node ref="VR2" pin="2" pintype="passive"/>
    </net>
    <net code="16" name="Net-(J2-VBUS)" class="Default">
      <node ref="F1" pin="2" pintype="passive"/>
      <node ref="J2" pin="1" pinfunction="VBUS" pintype="power_out"/>
      <node ref="TP3" pin="1" pinfunction="1" pintype="passive"/>
    </net>
    <net code="17" name="Net-(J3-Pin_1)" class="Default">
      <node ref="J3" pin="1" pinfunction="Pin_1" pintype="passive"/>
      <node ref="U1" pin="22" pinfunction="PC7" pintype="bidirectional"/>
    </net>
    <net code="18" name="Net-(J3-Pin_2)" class="Default">
      <node ref="J3" pin="2" pinfunction="Pin_2" pintype="passive"/>
      <node ref="U1" pin="23" pinfunction="PC6" pintype="bidirectional"/>
    </net>
    <net code="19" name="Net-(J3-Pin_3)" class="Default">
      <node ref="J3" pin="3" pinfunction="Pin_3" pintype="passive"/>
      <node ref="U1" pin="25" pinfunction="PC5" pintype="bidirectional"/>
    </net>
    <net code="20" name="Net-(J3-Pin_4)" class="Default">
      <node ref="J3" pin="4" pinfunction="Pin_4" pintype="passive"/>
      <node ref="U1" pin="26" pinfunction="PC4" pintype="bidirectional"/>
    </net>
    <net code="21" name="Net-(J3-Pin_5)" class="Default">
      <node ref="J3" pin="5" pinfunction="Pin_5" pintype="passive"/>
      <node ref="U1" pin="5" pinfunction="PC2" pintype="bidirectional"/>
    </net>
    <net code="22" name="Net-(J4-Pin_1)" class="Default">
      <node ref="J4" pin="1" pinfunction="Pin_1" pintype="passive"/>
      <node ref="U1" pin="18" pinfunction="PB4" pintype="bidirectional"/>
    </net>
    <net code="23" name="Net-(J4-Pin_2)" class="Default">
      <node ref="J4" pin="2" pinfunction="Pin_2" pintype="passive"/>
      <node ref="U1" pin="20" pinfunction="PB6" pintype="bidirectional"/>
    </net>
    <net code="24" name="Net-(J4-Pin_3)" class="Default">
      <node ref="J4" pin="3" pinfunction="Pin_3" pintype="passive"/>
      <node ref="U1" pin="19" pinfunction="PB5" pintype="bidirectional"/>
    </net>
    <net code="25" name="Net-(J4-Pin_4)" class="Default">
      <node ref="J4" pin="4" pinfunction="Pin_4" pintype="passive"/>
      <node ref="U1" pin="21" pinfunction="PB7" pintype="bidirectional"/>
    </net>
    <net code="26" name="Net-(J6-Pin_1)" class="Default">
      <node ref="C8" pin="2" pintype="passive"/>
      <node ref="J6" pin="1" pinfunction="Pin_1" pintype="passive"/>
    </net>
    <net code="27" name="Net-(J6-Pin_2)" class="Default">
      <node ref="J6" pin="2" pinfunction="Pin_2" pintype="passive"/>
      <node ref="U1" pin="12" pinfunction="PD6" pintype="bidirectional"/>
    </net>
    <net code="28" name="Net-(J6-Pin_3)" class="Default">
      <node ref="J6" pin="3" pinfunction="Pin_3" pintype="passive"/>
      <node ref="U1" pin="9" pinfunction="PD3" pintype="bidirectional"/>
    </net>
    <net code="29" name="Net-(J6-Pin_4)" class="Default">
      <node ref="J6" pin="4" pinfunction="Pin_4" pintype="passive"/>
      <node ref="U1" pin="8" pinfunction="PD2" pintype="bidirectional"/>
    </net>
    <net code="30" name="Net-(J6-Pin_5)" class="Default">
      <node ref="J6" pin="5" pinfunction="Pin_5" pintype="passive"/>
      <node ref="U1" pin="7" pinfunction="PD1" pintype="bidirectional"/>
    </net>
    <net code="31" name="Net-(J6-Pin_6)" class="Default">
      <node ref="J6" pin="6" pinfunction="Pin_6" pintype="passive"/>
      <node ref="U1" pin="6" pinfunction="PD0" pintype="bidirectional"/>
    </net>
    <net code="32" name="Net-(U1-D+)" class="Default">
      <node ref="R1" pin="1" pintype="passive"/>
      <node ref="U1" pin="29" pinfunction="D+" pintype="bidirectional"/>
    </net>
    <net code="33" name="Net-(U1-D-)" class="Default">
      <node ref="R2" pin="1" pintype="passive"/>
      <node ref="TP9" pin="1" pinfunction="1" pintype="passive"/>
      <node ref="U1" pin="30" pinfunction="D-" pintype="bidirectional"/>
    </net>
    <net code="34" name="Net-(U1-PC0/XTAL2)" class="Default">
      <node ref="C4" pin="1" pintype="passive"/>
      <node ref="R3" pin="2" pintype="passive"/>
      <node ref="TP8" pin="1" pinfunction="1" pintype="passive"/>
      <node ref="U1" pin="2" pinfunction="PC0/XTAL2" pintype="bidirectional"/>
      <node ref="Y1" pin="2" pinfunction="2" pintype="passive"/>
    </net>
    <net code="35" name="Net-(U1-UCAP)" class="Default">
      <node ref="C5" pin="1" pintype="passive"/>
      <node ref="U1" pin="27" pinfunction="UCAP" pintype="passive"/>
    </net>
    <net code="36" name="Net-(U1-XTAL1)" class="Default">
      <node ref="C3" pin="1" pintype="passive"/>
      <node ref="R3" pin="1" pintype="passive"/>
      <node ref="TP6" pin="1" pinfunction="1" pintype="passive"/>
      <node ref="U1" pin="1" pinfunction="XTAL1" pintype="input"/>
      <node ref="Y1" pin="1" pinfunction="1" pintype="passive"/>
    </net>
    <net code="37" name="VBUS" class="Default">
      <node ref="C6" pin="1" pintype="passive"/>
      <node ref="F1" pin="1" pintype="passive"/>
      <node ref="TP2" pin="1" pinfunction="1" pintype="passive"/>
      <node ref="U1" pin="31" pinfunction="UVCC" pintype="power_in"/>
    </net>
    <net code="38" name="unconnected-(U1-PB0-Pad14)" class="Default">
      <node ref="U1" pin="14" pinfunction="PB0" pintype="bidirectional+no_connect"/>
    </net>
  </nets>
</export>
